README.md
setup.cfg
setup.py
aimp_sdk.egg-info/PKG-INFO
aimp_sdk.egg-info/SOURCES.txt
aimp_sdk.egg-info/dependency_links.txt
aimp_sdk.egg-info/requires.txt
aimp_sdk.egg-info/top_level.txt
onepanel/__init__.py
onepanel/core/__init__.py
onepanel/core/api/__init__.py
onepanel/core/api/api_client.py
onepanel/core/api/configuration.py
onepanel/core/api/exceptions.py
onepanel/core/api/rest.py
onepanel/core/api/api/__init__.py
onepanel/core/api/api/auth_service_api.py
onepanel/core/api/api/config_service_api.py
onepanel/core/api/api/cron_workflow_service_api.py
onepanel/core/api/api/file_service_api.py
onepanel/core/api/api/inference_service_api.py
onepanel/core/api/api/label_service_api.py
onepanel/core/api/api/namespace_service_api.py
onepanel/core/api/api/secret_service_api.py
onepanel/core/api/api/service_service_api.py
onepanel/core/api/api/workflow_service_api.py
onepanel/core/api/api/workflow_template_service_api.py
onepanel/core/api/api/workspace_service_api.py
onepanel/core/api/api/workspace_template_service_api.py
onepanel/core/api/models/__init__.py
onepanel/core/api/models/add_secret_key_value_response.py
onepanel/core/api/models/add_workflow_executions_metrics_request.py
onepanel/core/api/models/archive_workflow_template_response.py
onepanel/core/api/models/container.py
onepanel/core/api/models/create_inference_service_request.py
onepanel/core/api/models/create_workflow_execution_body.py
onepanel/core/api/models/create_workspace_body.py
onepanel/core/api/models/cron_workflow.py
onepanel/core/api/models/cron_workflow_statistics_report.py
onepanel/core/api/models/delete_secret_key_response.py
onepanel/core/api/models/delete_secret_response.py
onepanel/core/api/models/env.py
onepanel/core/api/models/file.py
onepanel/core/api/models/get_access_token_request.py
onepanel/core/api/models/get_access_token_response.py
onepanel/core/api/models/get_config_response.py
onepanel/core/api/models/get_infer_token_request.py
onepanel/core/api/models/get_infer_token_response.py
onepanel/core/api/models/get_inference_service_response.py
onepanel/core/api/models/get_labels_response.py
