Metadata-Version: 2.1
Name: aimp-sdk
Version: 0.0.5
Summary: Python SDK for Onepanel
Home-page: https://github.com/onepanelio/core
Author: Onepanel, Inc.
Author-email: support@onepanel.io
License: UNKNOWN
Keywords: onepanel,computer-vision,deep-learning,ai,mlops
Platform: UNKNOWN
Classifier: Programming Language :: Python :: 3
Classifier: License :: OSI Approved :: Apache Software License
Classifier: Operating System :: OS Independent
Requires-Python: >=3.6
